odoo/addons/request_document_exception/README.rst
odoo/addons/request_document_exception/__init__.py
odoo/addons/request_document_exception/__manifest__.py
odoo/addons/request_document_exception/data/request_exception_data.xml
odoo/addons/request_document_exception/i18n/request_document_exception.pot
odoo/addons/request_document_exception/models/__init__.py
odoo/addons/request_document_exception/models/exception_rule.py
odoo/addons/request_document_exception/models/request_document.py
odoo/addons/request_document_exception/models/request_order.py
odoo/addons/request_document_exception/readme/CONTRIBUTORS.rst
odoo/addons/request_document_exception/readme/DESCRIPTION.rst
odoo/addons/request_document_exception/security/ir.model.access.csv
odoo/addons/request_document_exception/static/description/icon.png
odoo/addons/request_document_exception/static/description/index.html
odoo/addons/request_document_exception/tests/__init__.py
odoo/addons/request_document_exception/tests/test_request_document_exception.py
odoo/addons/request_document_exception/views/request_order_view.xml
odoo/addons/request_document_exception/wizard/__init__.py
odoo/addons/request_document_exception/wizard/request_exception_confirm.py
odoo/addons/request_document_exception/wizard/request_exception_confirm_view.xml
odoo_addon_request_document_exception-18.0.1.0.0.2.dist-info/METADATA
odoo_addon_request_document_exception-18.0.1.0.0.2.dist-info/WHEEL
odoo_addon_request_document_exception-18.0.1.0.0.2.dist-info/top_level.txt
odoo_addon_request_document_exception-18.0.1.0.0.2.dist-info/RECORD
